rettxidentity/__init__.py
rettxidentity/_version.py
rettxidentity/canonicalize.py
rettxidentity/config.py
rettxidentity/enums.py
rettxidentity/errors.py
rettxidentity/match.py
rettxidentity/models.py
rettxidentity/normalize.py
rettxidentity/script.py
rettxidentity/similarity.py
rettxidentity/transliterate.py
rettxidentity-0.2.0.dist-info/licenses/LICENSE
rettxidentity-0.2.0.dist-info/METADATA
rettxidentity-0.2.0.dist-info/WHEEL
rettxidentity-0.2.0.dist-info/top_level.txt
rettxidentity-0.2.0.dist-info/RECORD
