Metadata-Version: 2.4
Name: rettxidentity
Version: 0.2.0
Summary: Pure Python library for deterministic identity canonicalization and matching in the rettX ecosystem
Author: rettX Team
License: MIT
Project-URL: Homepage, https://github.com/rettx/rettxidentity
Project-URL: Documentation, https://github.com/rettx/rettxidentity#readme
Project-URL: Repository, https://github.com/rettx/rettxidentity
Project-URL: Issues, https://github.com/rettx/rettxidentity/issues
Keywords: identity,matching,canonicalization,rett-syndrome,rare-disease
Classifier: Development Status :: 3 - Alpha
Classifier: Intended Audience :: Developers
Classifier: License :: OSI Approved :: MIT License
Classifier: Programming Language :: Python :: 3
Classifier: Programming Language :: Python :: 3.10
Classifier: Programming Language :: Python :: 3.11
Classifier: Programming Language :: Python :: 3.12
Classifier: Topic :: Scientific/Engineering :: Medical Science Apps.
Classifier: Typing :: Typed
Requires-Python: >=3.10
License-File: LICENSE
Requires-Dist: transliterate>=1.10.2
Requires-Dist: rapidfuzz>=3.0
Provides-Extra: dev
Requires-Dist: pytest>=7.0; extra == "dev"
Requires-Dist: pytest-cov>=4.0; extra == "dev"
Requires-Dist: black>=23.0; extra == "dev"
Requires-Dist: ruff>=0.1; extra == "dev"
Requires-Dist: mypy>=1.0; extra == "dev"
Dynamic: license-file
